stratuxcot/__init__.py
stratuxcot/classes.py
stratuxcot/commands.py
stratuxcot/constants.py
stratuxcot/functions.py
stratuxcot-5.1.0.dist-info/LICENSE
stratuxcot-5.1.0.dist-info/METADATA
stratuxcot-5.1.0.dist-info/WHEEL
stratuxcot-5.1.0.dist-info/entry_points.txt
stratuxcot-5.1.0.dist-info/top_level.txt
stratuxcot-5.1.0.dist-info/RECORD
