Metadata-Version: 2.1
Name: stratuxcot
Version: 5.1.0
Summary: Stratux Cursor-on-Target Gateway.
Home-page: https://github.com/ampledata/stratuxcot
Author: Greg Albrecht
Author-email: oss@undef.net
License: Apache License, Version 2.0
Keywords: ADS-B,ADSB,Cursor on Target,ATAK,TAK,CoT
Classifier: Topic :: Communications :: Ham Radio
Classifier: Programming Language :: Python
Classifier: License :: OSI Approved :: Apache Software License
License-File: LICENSE
Requires-Dist: pytak (>=5.4.0)
Requires-Dist: aircot
Requires-Dist: websockets
